{
	"song": {
		"speed": 2.3,
		"stage": "philly",
		"player1": "bf",
		"player2": "pico",
		"player3": null,
		"events": [
			[
				11545.4545454545,
				[
					[
						"Philly Glow",
						"1",
						""
					]
				]
			],
			[
				11727.2727272727,
				[
					[
						"Philly Glow",
						"1",
						""
					]
				]
			],
			[
				11818.1818181818,
				[
					[
						"Philly Glow",
						"1",
						""
					]
				]
			],
			[
				11909.0909090909,
				[
					[
						"Philly Glow",
						"1",
						""
					]
				]
			],
			[
				12000,
				[
					[
						"Philly Glow",
						"1",
						""
					]
				]
			],
			[
				12090.9090909091,
				[
					[
						"Philly Glow",
						"1",
						""
					]
				]
			],
			[
				12234.0909090909,
				[
					[
						"Philly Glow",
						"2",
						""
					]
				]
			],
			[
				12518.1818181818,
				[
					[
						"Philly Glow",
						"2",
						""
					]
				]
			],
			[
				12852.2727272727,
				[
					[
						"Philly Glow",
						"2",
						""
					]
				]
			],
			[
				13000,
				[
					[
						"Philly Glow",
						"2",
						""
					]
				]
			],
			[
				13090.9090909091,
				[
					[
						"Philly Glow",
						"1",
						""
					]
				]
			],
			[
				13361.3636363636,
				[
					[
						"Philly Glow",
						"2",
						""
					]
				]
			],
			[
				13602.2727272727,
				[
					[
						"Philly Glow",
						"2",
						""
					]
				]
			],
			[
				13804.5454545455,
				[
					[
						"Philly Glow",
						"2",
						""
					]
				]
			],
			[
				14013.6363636364,
				[
					[
						"Philly Glow",
						"2",
						""
					]
				]
			],
			[
				14420.4545454545,
				[
					[
						"Philly Glow",
						"2",
						""
					]
				]
			],
			[
				14779.5454545455,
				[
					[
						"Philly Glow",
						"1",
						""
					]
				]
			],
			[
				15050,
				[
					[
						"Philly Glow",
						"2",
						""
					]
				]
			],
			[
				15706.8181818182,
				[
					[
						"Philly Glow",
						"2",
						""
					]
				]
			],
			[
				16727.2727272727,
				[
					[
						"Philly Glow",
						"2",
						""
					]
				]
			],
			[
				17418.1818181818,
				[
					[
						"Philly Glow",
						"2",
						""
					]
				]
			],
			[
				17454.5454545455,
				[
					[
						"Philly Glow",
						"0",
						""
					]
				]
			],
			[
				32090.9090909091,
				[
					[
						"Smooth cam zoom",
						"1.9",
						""
					]
				]
			],
			[
				34975,
				[
					[
						"Smooth cam zoom",
						"",
						""
					],
					[
						"LinearSpin",
						"361",
						"360"
					],
					[
						"Hide Hud",
						"1",
						""
					]
				]
			],
			[
				35068.1818181818,
				[
					[
						"Smooth cam zoom",
						"1.1",
						"2"
					]
				]
			],
			[
				40497.7272727273,
				[
					[
						"Hide Hud",
						"2",
						""
					],
					[
						"Play Animation",
						"scared",
						"bf"
					]
				]
			]
		],
		"notes": [],
		"splashSkin": null,
		"validScore": false,
		"gfVersion": "gf",
		"bpm": 165,
		"arrowSkin": null,
		"needsVoices": true,
		"song": "Blammed"
	}
}